sap_ber_client/__init__.py
sap_ber_client/ber_api_client.py
sap_ber_client/constants.py
sap_ber_client/http_client_base.py
sap_ber_client/http_request_retry.py
sap_business_entity_recognition_client_library-1.3.dist-info/LICENSE
sap_business_entity_recognition_client_library-1.3.dist-info/METADATA
sap_business_entity_recognition_client_library-1.3.dist-info/WHEEL
sap_business_entity_recognition_client_library-1.3.dist-info/top_level.txt
sap_business_entity_recognition_client_library-1.3.dist-info/RECORD
